setup.py
IOXhop_MCUio/__init__.py
IOXhop_MCUio.egg-info/PKG-INFO
IOXhop_MCUio.egg-info/SOURCES.txt
IOXhop_MCUio.egg-info/dependency_links.txt
IOXhop_MCUio.egg-info/top_level.txt