Metadata-Version: 1.0
Name: IOXhop-MCUio
Version: 0.1.2
Summary: Use your mcu to i/o expansion via I2C interface with Python
Home-page: https://github.com/ioxhop/IOXhop_MCUio_Python
Author: IOXhop
Author-email: max30012540@hotmail.com
License: UNKNOWN
Keywords: i/o expansion,Arduino,Raspberry Pi
Platform: UNKNOWN
